{"data":{"action":"world\/info\/upliftium","status":"success","message":"Fetched upliftium info!","payload":{"wallets":6185,"numTransactions":452413,"issuedSupply":21344130487,"crystallized":14057000000,"melted":7119000000,"nftCirculation":6938000000,"onBalanceCirculation":8487002470,"totalCirculation":15425002470,"transactions":{"byType":[{"numTransactions":206100,"actionType":"claimDrip"},{"numTransactions":116346,"actionType":"inGameShop"},{"numTransactions":80736,"actionType":"regionRewards"},{"numTransactions":33764,"actionType":"playerRewards"},{"numTransactions":7347,"actionType":"crystallizeNFT"},{"numTransactions":7119,"actionType":"meltNFT"},{"numTransactions":721,"actionType":"pictureInstall"},{"numTransactions":232,"actionType":"portalInstall"},{"numTransactions":22,"actionType":"screenshots"},{"numTransactions":11,"actionType":"landRegen"},{"numTransactions":8,"actionType":"syncGameBalance"},{"numTransactions":2,"actionType":"railRegen"},{"numTransactions":2,"actionType":"correction"},{"numTransactions":2,"actionType":"refund"},{"numTransactions":1,"actionType":"resetBalance"}],"total":452413},"claimable":2616352711.365203,"numLinkedAccounts":8890}}}